{"cameraMode":{"drawMode":0,"name":"Shaded","section":"Shading Mode"},"sceneLighting":false,"audioPlay":false,"sceneViewState":{"m_AlwaysRefresh":false,"showFog":true,"showSkybox":false,"showFlares":true,"showImageEffects":true,"showParticleSystems":true,"showVisualEffectGraphs":true,"m_FxEnabled":true},"in2DMode":false,"pivot":{"x":406.14056396484377,"y":204.98544311523438,"z":-10.839649200439454},"rotation":{"x":0.15213951468467713,"y":-0.7189918160438538,"z":0.1663840264081955,"w":0.6574362516403198},"size":463.075927734375,"orthographic":false}